haru/__init__.py
haru/communicator.py
haru/mixins.py
haru/protocol.py
haru-0.1.0.dist-info/LICENSE
haru-0.1.0.dist-info/WHEEL
haru-0.1.0.dist-info/METADATA
haru-0.1.0.dist-info/RECORD
