Metadata-Version: 2.1
Name: haru
Version: 0.1.0
Summary: Higher level aio subprocess protocol impl
Author: mooncell07
Author-email: mooncell07@users.noreply.github.com
Requires-Python: >=3.9,<4.0
Classifier: Programming Language :: Python :: 3
Classifier: Programming Language :: Python :: 3.10
Classifier: Programming Language :: Python :: 3.9
